heaobject/__init__.py
heaobject/account.py
heaobject/activity.py
heaobject/attribute.py
heaobject/aws.py
heaobject/awss3key.py
heaobject/bucket.py
heaobject/collaborator.py
heaobject/data.py
heaobject/dataadapter.py
heaobject/dataelement.py
heaobject/datamodel.py
heaobject/datapattern.py
heaobject/datatransform.py
heaobject/decorators.py
heaobject/encryption.py
heaobject/error.py
heaobject/folder.py
heaobject/group.py
heaobject/keychain.py
heaobject/mimetype.py
heaobject/organization.py
heaobject/person.py
heaobject/project.py
heaobject/py.typed
heaobject/record.py
heaobject/registry.py
heaobject/root.py
heaobject/scrubber.py
heaobject/settings.py
heaobject/source.py
heaobject/source2target.py
heaobject/storage.py
heaobject/trash.py
heaobject/user.py
heaobject/util.py
heaobject/volume.py
heaobject-1.36.0.dist-info/licenses/LICENSE
heaobject-1.36.0.dist-info/METADATA
heaobject-1.36.0.dist-info/WHEEL
heaobject-1.36.0.dist-info/top_level.txt
heaobject-1.36.0.dist-info/RECORD
