Metadata-Version: 2.4
Name: heaobject
Version: 1.36.0
Summary: Data and other classes that are passed into and out of HEA REST APIs.
Home-page: https://risr.hci.utah.edu
Author: Research Informatics Shared Resource, Huntsman Cancer Institute, Salt Lake City, UT
Author-email: Andrew.Post@hci.utah.edu
License: Apache License 2.0
Classifier: Development Status :: 5 - Production/Stable
Classifier: Environment :: Console
Classifier: Intended Audience :: Developers
Classifier: Natural Language :: English
Classifier: Operating System :: OS Independent
Classifier: Programming Language :: Python
Classifier: Programming Language :: Python :: 3
Classifier: Programming Language :: Python :: 3.10
Classifier: Programming Language :: Python :: 3.11
Classifier: Programming Language :: Python :: 3.12
Classifier: Programming Language :: Python :: Implementation :: CPython
Classifier: Topic :: Software Development
Classifier: Topic :: Scientific/Engineering
Classifier: Topic :: Scientific/Engineering :: Bio-Informatics
Classifier: Topic :: Scientific/Engineering :: Information Analysis
Classifier: Topic :: Scientific/Engineering :: Medical Science Apps.
Requires-Python: >=3.10
License-File: LICENSE
Requires-Dist: multidict~=6.1.0
Requires-Dist: yarl~=1.18.3
Requires-Dist: humanize~=4.11.0
Requires-Dist: email-validator~=2.3.0
Requires-Dist: uritemplate~=4.1.1
Requires-Dist: python-dateutil~=2.9.0.post0
Requires-Dist: tzlocal~=5.2
Requires-Dist: orjson~=3.10.12
Requires-Dist: babel~=2.16.0
Requires-Dist: pyxdg~=0.28
Requires-Dist: types-pyxdg~=0.28.0.20250622
Requires-Dist: wrapt~=1.17.2
Requires-Dist: cryptography~=44.0.0
Dynamic: author
Dynamic: author-email
Dynamic: classifier
Dynamic: description
Dynamic: description-content-type
Dynamic: home-page
Dynamic: license
Dynamic: license-file
Dynamic: requires-dist
Dynamic: requires-python
Dynamic: summary
